{
  "templates": {
    "type": "JSON",
    "content": [
      {
        "id": "69-7560252",
        "Flight": "AA1601",
        "Time": "10:55",
        "HotelName": "Royalton Splash Riviera Cancun"
      },
      {
        "id": "4128538",
        "Flight": "DL1878",
        "Time": "14:06",
        "HotelName": "Royalton Splash Riviera Cancun"
      },
      {
        "id": "4119914",
        "Flight": "DL1878",
        "Time": "14:06",
        "HotelName": "Royalton Splash Riviera Cancun"
      },
      {
        "id": "4107210",
        "Flight": "NOT CONFIRMED",
        "Time": "⚠️",
        "HotelName": "CONTACT YOUR ROYALTON EXPERIENCE REP"
      },
      {
        "id": "4118415",
        "Flight": "DL1878",
        "Time": "14:06",
        "HotelName": "Royalton Splash Riviera Cancun"
      },
      {
        "id": "4107210",
        "Flight": "NOT CONFIRMED",
        "Time": "⚠️",
        "HotelName": "CONTACT YOUR ROYALTON EXPERIENCE REP"
      },
      {
        "id": "4128561",
        "Flight": "DL1878",
        "Time": "14:06",
        "HotelName": "Royalton Splash Riviera Cancun"
      },
      {
        "id": "4107210",
        "Flight": "AA1185",
        "Time": "11:05",
        "HotelName": "Royalton Splash Riviera Cancun"
      },
      {
        "id": "3879265",
        "Flight": "AA2175",
        "Time": "12:39",
        "HotelName": "Royalton Splash Riviera Cancun"
      }
    ],
    "source": {
      "data_source": "Google Sheets (Private)",
      "update_frequency": "Automated"
    }
  }
}