{
  "templates": {
    "type": "JSON",
    "content": [
      {
        "id": "4263138",
        "Flight": "AM4595",
        "PickupDate": "2025-07-17",
        "PickupTime": "08:55",
        "HotelName": "Royalton Splash Riviera Cancun",
        "HotelNumber": 18866
      },
      {
        "id": "3624403",
        "Flight": "WS2425",
        "PickupDate": "2025-07-17",
        "PickupTime": "09:20",
        "HotelName": "Royalton Splash Riviera Cancun",
        "HotelNumber": 18866
      },
      {
        "id": "4263158",
        "Flight": "DL620",
        "PickupDate": "2025-07-17",
        "PickupTime": "08:55",
        "HotelName": "Royalton Splash Riviera Cancun",
        "HotelNumber": 18866
      },
      {
        "id": "4263110",
        "Flight": "DL620",
        "PickupDate": "2025-07-17",
        "PickupTime": "08:55",
        "HotelName": "Royalton Splash Riviera Cancun",
        "HotelNumber": 18866
      },
      {
        "id": "Q3K9GK",
        "Flight": "B61014",
        "PickupDate": "2025-07-17",
        "PickupTime": "12:00",
        "HotelName": "Royalton Splash Riviera Cancun",
        "HotelNumber": 18866
      }
    ],
    "source": {
      "data_source": "Google Sheets (Private)",
      "update_frequency": "Automated"
    }
  }
}